{"prefix":"j","token_count":15,"tokens":[{"token":"Java","relationships":{"≡":[{"token":"Java Programming Language","weight":0.95}],"⊃":[{"token":"Programming Languages","weight":0.9},{"token":"Object-Oriented Languages","weight":0.85}],"⊂":[{"token":"JavaScript","weight":0.7},{"token":"Python","weight":0.65}],"≈":[{"token":"Kotlin","weight":0.8},{"token":"Scala","weight":0.75}],"∈":[{"token":"High-Level Programming Language","weight":0.85}],"⊤":[{"token":"Software Development","weight":0.9}],"⊛":[{"token":"Spring Framework","weight":0.78},{"token":"Java Virtual Machine","weight":0.8}],"∝":[{"token":"Software Engineering","weight":0.76}],"⇄":[{"token":"C++","weight":0.68},{"token":"C#","weight":0.66}],"↔":[{"token":"Android Development","weight":0.72}],"⊗":[{"token":"OpenJDK","weight":0.73},{"token":"Apache Ant","weight":0.7}],"∗":[{"token":"Enterprise Applications","weight":0.74}]},"cached_at":"2025-10-26T05:34:25.426Z"},{"token":"jog","relationships":{"≡":[{"token":"run","weight":0.95}],"≈":[{"token":"sprint","weight":0.8},{"token":"trot","weight":0.7}],"∈":[{"token":"physical activity","weight":0.9}],"⊕":[{"token":"exercise","weight":0.85}],"∗":[{"token":"health","weight":0.8}],"⇄":[{"token":"running shoes","weight":0.75},{"token":"track","weight":0.65}],"⊛":[{"token":"outdoor activity","weight":0.7}],"⇒":[{"token":"fitness","weight":0.9}]},"cached_at":"2025-10-26T16:42:17.969Z"},{"token":"join","relationships":{"≡":[{"token":"connect","weight":0.95},{"token":"link","weight":0.93}],"⊃":[{"token":"group","weight":0.8},{"token":"team","weight":0.75}],"⊂":[{"token":"network","weight":0.85},{"token":"community","weight":0.78}],"≈":[{"token":"merge","weight":0.7},{"token":"unite","weight":0.68}],"∈":[{"token":"collection","weight":0.66},{"token":"set","weight":0.64}],"⊕":[{"token":"collaborate","weight":0.72},{"token":"cooperate","weight":0.7}],"⊛":[{"token":"integration","weight":0.74},{"token":"association","weight":0.71}],"⇄":[{"token":"interaction","weight":0.69},{"token":"engagement","weight":0.67}],"⇝":[{"token":"contribute","weight":0.65},{"token":"support","weight":0.63}]},"cached_at":"2025-10-26T17:21:20.194Z"},{"token":"joined","relationships":{"≡":[{"token":"united","weight":0.95},{"token":"combined","weight":0.9}],"⊃":[{"token":"group","weight":0.85},{"token":"team","weight":0.8}],"⊂":[{"token":"partnership","weight":0.75}],"≈":[{"token":"merged","weight":0.88},{"token":"linked","weight":0.82}],"∈":[{"token":"collaboration","weight":0.7}],"⊕":[{"token":"synergy","weight":0.78}],"⊛":[{"token":"connection","weight":0.76}],"→":[{"token":"converged","weight":0.74}],"⇌":[{"token":"intertwined","weight":0.65}],"∗":[{"token":"integrates","weight":0.72}],"⚡":[{"token":"memory","weight":0.68}]},"cached_at":"2025-10-26T03:33:30.887Z"},{"token":"joint","relationships":{"≡":[{"token":"connection","weight":0.95}],"⊃":[{"token":"knee","weight":0.85},{"token":"elbow","weight":0.8}],"⊂":[{"token":"body","weight":0.9},{"token":"limb","weight":0.75}],"≈":[{"token":"link","weight":0.7}],"∈":[{"token":"anatomy","weight":0.8}],"⊕":[{"token":"flexibility","weight":0.65}],"⊛":[{"token":"movement","weight":0.6}],"⇝":[{"token":"stability","weight":0.55}],"↔":[{"token":"hinge","weight":0.5}],"∝":[{"token":"mobility","weight":0.45}]},"cached_at":"2025-10-26T15:42:11.580Z"},{"token":"joint effort","relationships":{"≡":[{"token":"collaboration","weight":0.95},{"token":"teamwork","weight":0.9}],"⊃":[{"token":"project","weight":0.8},{"token":"task","weight":0.75}],"⊂":[{"token":"collaborative project","weight":0.85},{"token":"group effort","weight":0.82}],"≈":[{"token":"joint venture","weight":0.7},{"token":"cooperative endeavor","weight":0.68}],"∈":[{"token":"effort","weight":0.95}],"⊕":[{"token":"synergy","weight":0.78}],"⊛":[{"token":"partnership","weight":0.76}],"⇄":[{"token":"collaborate","weight":0.8}],"∗":[{"token":"motivation","weight":0.65}]},"cached_at":"2025-10-26T06:36:45.335Z"},{"token":"joint venture","relationships":{"≡":[{"token":"partnership","weight":0.95},{"token":"collaboration","weight":0.9}],"⊃":[{"token":"business arrangement","weight":0.85}],"⊂":[{"token":"strategic alliance","weight":0.8}],"≈":[{"token":"cooperative agreement","weight":0.75}],"∈":[{"token":"contract","weight":0.7}],"⊏":[{"token":"investment","weight":0.65}],"⊐":[{"token":"company","weight":0.6}],"≛":[{"token":"merger","weight":0.55}],"⊕":[{"token":"joint ownership","weight":0.5}],"⊛":[{"token":"collaborative project","weight":0.45}],"⇌":[{"token":"risk sharing","weight":0.4}],"∝":[{"token":"profit sharing","weight":0.35}],"⋆":[{"token":"business development","weight":0.3}],"⇄":[{"token":"joint marketing","weight":0.25}]},"cached_at":"2025-10-26T15:43:45.043Z"},{"token":"jointly","relationships":{"≡":[{"token":"together","weight":0.95}],"∈":[{"token":"collaboration","weight":0.9},{"token":"cooperation","weight":0.85}],"⊕":[{"token":"combined","weight":0.8}],"∝":[{"token":"mutual","weight":0.75}],"⇄":[{"token":"simultaneously","weight":0.7}],"⊛":[{"token":"partnership","weight":0.65}],"⊐":[{"token":"teamwork","weight":0.6}],"∼":[{"token":"concurrently","weight":0.55}],"≈":[{"token":"joint","weight":0.5}]},"cached_at":"2025-10-26T04:09:04.121Z"},{"token":"journal","relationships":{"≡":[{"token":"diary","weight":0.95}],"⊃":[{"token":"article","weight":0.8},{"token":"entry","weight":0.75}],"⊂":[{"token":"research publication","weight":0.7},{"token":"daily log","weight":0.65}],"≈":[{"token":"magazine","weight":0.6}],"∈":[{"token":"literature","weight":0.85},{"token":"media","weight":0.8}],"⊕":[{"token":"notebook","weight":0.55}],"⊛":[{"token":"blog","weight":0.5}],"⇄":[{"token":"news","weight":0.45}],"∗":[{"token":"reflection","weight":0.65}],"⋆":[{"token":"record","weight":0.7}]},"cached_at":"2025-10-26T04:52:46.592Z"},{"token":"journey","relationships":{"≡":[{"token":"adventure","weight":0.95}],"≈":[{"token":"expedition","weight":0.85},{"token":"voyage","weight":0.8}],"∈":[{"token":"experience","weight":0.9}],"⊕":[{"token":"growth","weight":0.75}],"⇝":[{"token":"transformation","weight":0.7}],"⊛":[{"token":"exploration","weight":0.65}],"→":[{"token":"destination","weight":0.6}],"⇒":[{"token":"progression","weight":0.55}],"∝":[{"token":"change","weight":0.5}]},"cached_at":"2025-10-26T03:36:52.006Z"},{"token":"joy","relationships":{"≡":[{"token":"happiness","weight":0.95},{"token":"delight","weight":0.9}],"⊃":[{"token":"emotion","weight":0.85}],"⊂":[{"token":"euphoria","weight":0.8}],"≈":[{"token":"pleasure","weight":0.75}],"∈":[{"token":"feeling","weight":0.7}],"⊕":[{"token":"contentment","weight":0.65}],"⊛":[{"token":"celebration","weight":0.6}],"⇝":[{"token":"positivity","weight":0.55}],"∗":[{"token":"laughter","weight":0.5}],"⋆":[{"token":"cheerfulness","weight":0.45}],"⇄":[{"token":"love","weight":0.4}],"∝":[{"token":"satisfaction","weight":0.35}]},"cached_at":"2025-10-26T16:32:16.819Z"},{"token":"judgment","relationships":{"≡":[{"token":"decision","weight":0.95},{"token":"verdict","weight":0.9}],"⊃":[{"token":"evaluation","weight":0.8},{"token":"assessment","weight":0.75}],"⊂":[{"token":"court ruling","weight":0.7},{"token":"legal finding","weight":0.65}],"≈":[{"token":"opinion","weight":0.6},{"token":"conclusion","weight":0.55}],"∈":[{"token":"legal concept","weight":0.85},{"token":"ethical principle","weight":0.7}],"⊤":[{"token":"cognitive process","weight":0.75},{"token":"judicial process","weight":0.65}],"⊛":[{"token":"discretion","weight":0.6},{"token":"intuition","weight":0.55}],"⇝":[{"token":"decision-making","weight":0.8},{"token":"moral judgment","weight":0.7}],"∗":[{"token":"consequence","weight":0.5},{"token":"rationale","weight":0.45}],"⊕":[{"token":"interpretation","weight":0.65},{"token":"reasoning","weight":0.6}],"⊨":[{"token":"evidence","weight":0.55},{"token":"justification","weight":0.5}]},"cached_at":"2025-10-26T09:02:19.076Z"},{"token":"justice","relationships":{"≡":[{"token":"fairness","weight":0.95},{"token":"equity","weight":0.9}],"⊃":[{"token":"law","weight":0.85},{"token":"morality","weight":0.8}],"⊂":[{"token":"criminal justice","weight":0.75},{"token":"social justice","weight":0.7}],"≈":[{"token":"righteousness","weight":0.6},{"token":"honesty","weight":0.55}],"∈":[{"token":"ethics","weight":0.65},{"token":"human rights","weight":0.6}],"⊛":[{"token":"equality","weight":0.75},{"token":"accountability","weight":0.7}],"⇝":[{"token":"peace","weight":0.5},{"token":"social order","weight":0.45}],"∗":[{"token":"truth","weight":0.55},{"token":"trust","weight":0.5}],"⋆":[{"token":"freedom","weight":0.65},{"token":"duty","weight":0.6}],"⊕":[{"token":"compassion","weight":0.4},{"token":"responsibility","weight":0.45}],"⊘":[{"token":"injustice","weight":0.9},{"token":"oppression","weight":0.85}]},"cached_at":"2025-10-26T05:24:34.590Z"},{"token":"justification","relationships":{"≡":[{"token":"rationale","weight":0.95}],"⊃":[{"token":"argument","weight":0.85},{"token":"explanation","weight":0.8}],"⊂":[{"token":"reasoning","weight":0.9}],"≈":[{"token":"validation","weight":0.7}],"∈":[{"token":"ethical consideration","weight":0.65}],"⊕":[{"token":"support","weight":0.6}],"⊛":[{"token":"defense","weight":0.75}],"∗":[{"token":"exemplification","weight":0.55}],"⋆":[{"token":"justification theory","weight":0.5}],"⇝":[{"token":"conclusion","weight":0.65}],"⊨":[{"token":"evidence","weight":0.8}],"≠":[{"token":"rejection","weight":0.4}],"⊗":[{"token":"analysis","weight":0.55}]},"cached_at":"2025-10-26T17:26:42.148Z"},{"token":"just","relationships":{"≈":[{"token":"simply","weight":0.85},{"token":"only","weight":0.8}],"∈":[{"token":"adverb","weight":0.9}],"⊕":[{"token":"rather","weight":0.7}],"⇄":[{"token":"say","weight":0.75},{"token":"think","weight":0.65}],"∗":[{"token":"clarity","weight":0.6}],"⊏":[{"token":"phrase","weight":0.55}],"∼":[{"token":"hello","weight":0.05},{"token":"word","weight":0.05},{"token":"are","weight":0.05},{"token":"there","weight":0.05},{"token":"alex","weight":0.05},{"token":"but","weight":0.05},{"token":"...","weight":0.05},{"token":"go","weight":0.05},{"token":"verb","weight":0.05},{"token":"and","weight":0.05},{"token":"you","weight":0.05}]},"cached_at":"2025-10-29T00:39:12.194Z"}]}